gitlab_changelog_tool/__init__.py
gitlab_changelog_tool/__main__.py
gitlab_changelog_tool/api.py
gitlab_changelog_tool/cli.py
gitlab_changelog_tool/package.py
gitlab_changelog_tool/templates/CHANGELOG.md
gitlab_changelog_tool-1.0.2.dist-info/LICENSE.md
gitlab_changelog_tool-1.0.2.dist-info/METADATA
gitlab_changelog_tool-1.0.2.dist-info/WHEEL
gitlab_changelog_tool-1.0.2.dist-info/entry_points.txt
gitlab_changelog_tool-1.0.2.dist-info/top_level.txt
gitlab_changelog_tool-1.0.2.dist-info/RECORD
