Metadata-Version: 2.1
Name: gitlab-changelog-tool
Version: 1.0.2
Summary: Automatically generate changelogs from merge requests on GitLab.
Home-page: https://github.com/danilopeixoto/gitlab-changelog-tool
Download-URL: https://pypi.org/project/gitlab-changelog-tool
Author: Danilo Peixoto Ferreira
License: BSD-3-Clause
Project-URL: Code, https://github.com/danilopeixoto/gitlab-changelog-tool
Project-URL: Issue tracker, https://github.com/danilopeixoto/gitlab-changelog-tool/issues
Classifier: Programming Language :: Python
Classifier: Programming Language :: Python :: 3
Classifier: Programming Language :: Python :: 3.8
Classifier: License :: OSI Approved :: BSD License
Requires-Python: >=3.8.0
License-File: LICENSE.md
Requires-Dist: click (>=8.1.0)
Requires-Dist: jinja2 (>=3.1.0)
Requires-Dist: semver (>=3.0.0)
Requires-Dist: python-dateutil (>=2.8.0)
Requires-Dist: python-gitlab (>=3.14.0)
Provides-Extra: development
Requires-Dist: setuptools (>=58.2.0) ; extra == 'development'
Requires-Dist: wheel (>=0.37.0) ; extra == 'development'
Requires-Dist: autopep8 (>=1.6.0) ; extra == 'development'
Requires-Dist: isort (>=5.10.0) ; extra == 'development'
Requires-Dist: mypy (>=0.9.0) ; extra == 'development'
Requires-Dist: pylint (>=2.12.0) ; extra == 'development'
Requires-Dist: pytest (>=6.2.0) ; extra == 'development'
Requires-Dist: pytest-cov (>=3.0.0) ; extra == 'development'
Requires-Dist: twine (>=3.7.0) ; extra == 'development'
Requires-Dist: bump2version (>=1.0.0) ; extra == 'development'
